hitl_al_gomg/__init__.py
hitl_al_gomg/evaluate_results.py
hitl_al_gomg/path.py
hitl_al_gomg/run.py
hitl_al_gomg/utils.py
hitl_al_gomg/models/RandomForest.py
hitl_al_gomg/models/__init__.py
hitl_al_gomg/models/train.py
hitl_al_gomg/scoring/__init__.py
hitl_al_gomg/scoring/metrics.py
hitl_al_gomg/scoring/sascorer.py
hitl_al_gomg/scoring/write.py
hitl_al_gomg/synthitl/__init__.py
hitl_al_gomg/synthitl/acquisition.py
hitl_al_gomg/synthitl/epig.py
hitl_al_gomg/synthitl/simulated_expert.py
hitl_al_gomg-0.0.13.dist-info/LICENSE.txt
hitl_al_gomg-0.0.13.dist-info/METADATA
hitl_al_gomg-0.0.13.dist-info/WHEEL
hitl_al_gomg-0.0.13.dist-info/top_level.txt
hitl_al_gomg-0.0.13.dist-info/RECORD
