Metadata-Version: 2.1
Name: hitl_al_gomg
Version: 0.0.13
Summary: A Human-in-the-loop active learning workflow to improve molecular property predictors with human expert feedback for goal-oriented molecule generation.
Home-page: https://github.com/yasminenahal/hitl_al_gomg.git
Author: Yasmine Nahal
Author-email: yasmine.nahal@aalto.fi
License: MIT
Keywords: REINVENT,HITL,HITL_AL_GOMG
Classifier: Programming Language :: Python :: 3
Classifier: License :: OSI Approved :: MIT License
Classifier: Operating System :: OS Independent
Requires-Python: >=3.9, <3.11
License-File: LICENSE.txt
Requires-Dist: PyTDC==1.0.7
Requires-Dist: scipy==1.10.1
Requires-Dist: torch==1.12.1
Requires-Dist: fcd-torch==1.0.7
Requires-Dist: click==8.1.7
Requires-Dist: matplotlib==3.9.2
Requires-Dist: jupyter==1.1.1
